jqueryui/__init__.py
jqueryui/static/jquery/ui/1.11.4/jquery-ui.css
jqueryui/static/jquery/ui/1.11.4/jquery-ui.js
jqueryui/static/jquery/ui/1.11.4/jquery-ui.min.css
jqueryui/static/jquery/ui/1.11.4/jquery-ui.min.js
jqueryui/static/jquery/ui/1.11.4/jquery-ui.structure.css
jqueryui/static/jquery/ui/1.11.4/jquery-ui.structure.min.css
jqueryui/static/jquery/ui/1.11.4/jquery-ui.theme.css
jqueryui/static/jquery/ui/1.11.4/jquery-ui.theme.min.css
jqueryui/static/jquery/ui/1.11.4/images/ui-bg_diagonals-thick_18_b81900_40x40.png
jqueryui/static/jquery/ui/1.11.4/images/ui-bg_diagonals-thick_20_666666_40x40.png
jqueryui/static/jquery/ui/1.11.4/images/ui-bg_flat_10_000000_40x100.png
jqueryui/static/jquery/ui/1.11.4/images/ui-bg_glass_100_f6f6f6_1x400.png
jqueryui/static/jquery/ui/1.11.4/images/ui-bg_glass_100_fdf5ce_1x400.png
jqueryui/static/jquery/ui/1.11.4/images/ui-bg_glass_65_ffffff_1x400.png
jqueryui/static/jquery/ui/1.11.4/images/ui-bg_gloss-wave_35_f6a828_500x100.png
jqueryui/static/jquery/ui/1.11.4/images/ui-bg_highlight-soft_100_eeeeee_1x100.png
jqueryui/static/jquery/ui/1.11.4/images/ui-bg_highlight-soft_75_ffe45c_1x100.png
jqueryui/static/jquery/ui/1.11.4/images/ui-icons_222222_256x240.png
jqueryui/static/jquery/ui/1.11.4/images/ui-icons_228ef1_256x240.png
jqueryui/static/jquery/ui/1.11.4/images/ui-icons_ef8c08_256x240.png
jqueryui/static/jquery/ui/1.11.4/images/ui-icons_ffd27a_256x240.png
jqueryui/static/jquery/ui/1.11.4/images/ui-icons_ffffff_256x240.png
jqueryui/templatetags/__init__.py
jqueryui/templatetags/jqueryui.py
static_jqueryui-1.11.4.1.dist-info/DESCRIPTION.rst
static_jqueryui-1.11.4.1.dist-info/METADATA
static_jqueryui-1.11.4.1.dist-info/RECORD
static_jqueryui-1.11.4.1.dist-info/WHEEL
static_jqueryui-1.11.4.1.dist-info/metadata.json
static_jqueryui-1.11.4.1.dist-info/top_level.txt
