Metadata-Version: 2.0
Name: static-jqueryui
Version: 1.11.4.1
Summary: jQuery UI packaged in an handy django app to speed up new applications and deployment.
Home-page: https://github.com/wtayyeb/static-jqueryui
Author: wtayyeb
Author-email: wtayyeb@gmail.com
License: MIT
Keywords: django jqueryui staticfiles templatetags
Platform: UNKNOWN
Classifier: Development Status :: 5 - Production/Stable
Classifier: Environment :: Web Environment
Classifier: Framework :: Django
Classifier: Intended Audience :: Developers
Classifier: Natural Language :: English
Classifier: License :: OSI Approved :: MIT License
Classifier: Operating System :: OS Independent
Classifier: Programming Language :: Python
Classifier: Topic :: Utilities
Requires-Dist: django-appconf
